{"cameraMode":{"drawMode":0,"name":"Shaded","section":"Shading Mode"},"sceneLighting":false,"audioPlay":false,"sceneViewState":{"m_AlwaysRefresh":false,"showFog":true,"showSkybox":false,"showFlares":true,"showImageEffects":true,"showParticleSystems":true,"showVisualEffectGraphs":true,"m_FxEnabled":true},"in2DMode":false,"pivot":{"x":-0.3613802194595337,"y":-0.3115096092224121,"z":1.1782128810882569},"rotation":{"x":-0.2557196617126465,"y":0.3084862232208252,"z":-0.08644043654203415,"w":-0.9121895432472229},"size":1.214991807937622,"orthographic":false}